{
  "alya-sometimes-hides-her-feelings-in-russian-01.png": {
    "name": "Alya Sometimes Hides Her Feelings in Russian 1",
    "anime": "Alya Sometimes Hides Her Feelings in Russian",
    "section": "Wallpapers",
    "resolution": "1920x1080"
  },
  "alya-sometimes-hides-her-feelings-in-russian-02.png": {
    "name": "Alya Sometimes Hides Her Feelings in Russian 2",
    "anime": "Alya Sometimes Hides Her Feelings in Russian",
    "section": "Wallpapers",
    "resolution": "3840x2160"
  },
  "berserk-01.png": {
    "name": "Berserk 1",
    "anime": "Berserk",
    "section": "Wallpapers",
    "resolution": "1920x1080"
  },
  "berserk-02.jpg": {
    "name": "Berserk 2",
    "anime": "Berserk",
    "section": "Wallpapers",
    "resolution": "1920x1080"
  },
  "berserk-03.png": {
    "name": "Berserk 3",
    "anime": "Berserk",
    "section": "Wallpapers",
    "resolution": "1920x1080"
  },
  "chainsaw-man-01.png": {
    "name": "Chainsaw Man 1",
    "anime": "Chainsaw Man",
    "section": "Wallpapers",
    "resolution": "7680x4320"
  },
  "chainsaw-man-10.jpg": {
    "name": "Chainsaw Man 10",
    "anime": "Chainsaw Man",
    "section": "Wallpapers",
    "resolution": "3840x2159"
  },
  "chainsaw-man-11.jpg": {
    "name": "Chainsaw Man 11",
    "anime": "Chainsaw Man",
    "section": "Wallpapers",
    "resolution": "3840x1608"
  },
  "chainsaw-man-12.jpg": {
    "name": "Chainsaw Man 12",
    "anime": "Chainsaw Man",
    "section": "Wallpapers",
    "resolution": "3840x2160"
  },
  "chainsaw-man-13.png": {
    "name": "Chainsaw Man 13",
    "anime": "Chainsaw Man",
    "section": "Wallpapers",
    "resolution": "3840x2160"
  },
  "chainsaw-man-14.png": {
    "name": "Chainsaw Man 14",
    "anime": "Chainsaw Man",
    "section": "Wallpapers",
    "resolution": "3840x2160"
  },
  "chainsaw-man-15.png": {
    "name": "Chainsaw Man 15",
    "anime": "Chainsaw Man",
    "section": "Wallpapers",
    "resolution": "1920x1080"
  },
  "chainsaw-man-16.png": {
    "name": "Chainsaw Man 16",
    "anime": "Chainsaw Man",
    "section": "Wallpapers",
    "resolution": "7680x4320"
  },
  "chainsaw-man-02.png": {
    "name": "Chainsaw Man 2",
    "anime": "Chainsaw Man",
    "section": "Wallpapers",
    "resolution": "1920x1080"
  },
  "chainsaw-man-03.png": {
    "name": "Chainsaw Man 3",
    "anime": "Chainsaw Man",
    "section": "Wallpapers",
    "resolution": "1920x1080"
  },
  "chainsaw-man-04.png": {
    "name": "Chainsaw Man 4",
    "anime": "Chainsaw Man",
    "section": "Wallpapers",
    "resolution": "1920x1080"
  },
  "chainsaw-man-05.jpg": {
    "name": "Chainsaw Man 5",
    "anime": "Chainsaw Man",
    "section": "Wallpapers",
    "resolution": "5120x2880"
  },
  "chainsaw-man-06.jpg": {
    "name": "Chainsaw Man 6",
    "anime": "Chainsaw Man",
    "section": "Wallpapers",
    "resolution": "3600x2400"
  },
  "chainsaw-man-07.jpg": {
    "name": "Chainsaw Man 7",
    "anime": "Chainsaw Man",
    "section": "Wallpapers",
    "resolution": "3840x2160"
  },
  "chainsaw-man-08.jpg": {
    "name": "Chainsaw Man 8",
    "anime": "Chainsaw Man",
    "section": "Wallpapers",
    "resolution": "3840x2160"
  },
  "chainsaw-man-09.png": {
    "name": "Chainsaw Man 9",
    "anime": "Chainsaw Man",
    "section": "Wallpapers",
    "resolution": "2560x1440"
  },
  "charlotte-01.png": {
    "name": "Charlotte 1",
    "anime": "Charlotte",
    "section": "Wallpapers",
    "resolution": "1920x1080"
  },
  "charlotte-02.jpg": {
    "name": "Charlotte 2",
    "anime": "Charlotte",
    "section": "Wallpapers",
    "resolution": "3840x2160"
  },
  "code-geass-lelouch-of-the-rebellion-01.jpg": {
    "name": "Code Geass: Lelouch of the Rebellion 1",
    "anime": "Code Geass: Lelouch of the Rebellion",
    "section": "Wallpapers",
    "resolution": "1920x1080"
  },
  "code-geass-lelouch-of-the-rebellion-02.jpg": {
    "name": "Code Geass: Lelouch of the Rebellion 2",
    "anime": "Code Geass: Lelouch of the Rebellion",
    "section": "Wallpapers",
    "resolution": "1920x1080"
  },
  "code-geass-lelouch-of-the-rebellion-03.jpg": {
    "name": "Code Geass: Lelouch of the Rebellion 3",
    "anime": "Code Geass: Lelouch of the Rebellion",
    "section": "Wallpapers",
    "resolution": "1920x1080"
  },
  "code-geass-lelouch-of-the-rebellion-04.jpg": {
    "name": "Code Geass: Lelouch of the Rebellion 4",
    "anime": "Code Geass: Lelouch of the Rebellion",
    "section": "Wallpapers",
    "resolution": "4501x2813"
  },
  "darling-in-the-franxx-01.jpg": {
    "name": "DARLING in the FRANXX 1",
    "anime": "DARLING in the FRANXX",
    "section": "Wallpapers",
    "resolution": "2560x1440"
  },
  "darling-in-the-franxx-02.jpg": {
    "name": "DARLING in the FRANXX 2",
    "anime": "DARLING in the FRANXX",
    "section": "Wallpapers",
    "resolution": "2560x1440"
  },
  "darling-in-the-franxx-03.png": {
    "name": "DARLING in the FRANXX 3",
    "anime": "DARLING in the FRANXX",
    "section": "Wallpapers",
    "resolution": "1920x1080"
  },
  "darling-in-the-franxx-04.jpg": {
    "name": "DARLING in the FRANXX 4",
    "anime": "DARLING in the FRANXX",
    "section": "Wallpapers",
    "resolution": "3840x2160"
  },
  "darling-in-the-franxx-05.png": {
    "name": "DARLING in the FRANXX 5",
    "anime": "DARLING in the FRANXX",
    "section": "Wallpapers",
    "resolution": "8000x5000"
  },
  "darling-in-the-franxx-06.png": {
    "name": "DARLING in the FRANXX 6",
    "anime": "DARLING in the FRANXX",
    "section": "Wallpapers",
    "resolution": "1920x1080"
  },
  "darling-in-the-franxx-07.jpg": {
    "name": "DARLING in the FRANXX 7",
    "anime": "DARLING in the FRANXX",
    "section": "Wallpapers",
    "resolution": "1920x1167"
  },
  "darling-in-the-franxx-08.png": {
    "name": "DARLING in the FRANXX 8",
    "anime": "DARLING in the FRANXX",
    "section": "Wallpapers",
    "resolution": "1920x1080"
  },
  "darling-in-the-franxx-09.jpg": {
    "name": "DARLING in the FRANXX 9",
    "anime": "DARLING in the FRANXX",
    "section": "Wallpapers",
    "resolution": "3840x2160"
  },
  "date-a-live-01.png": {
    "name": "Date A Live 1",
    "anime": "Date A Live",
    "section": "Wallpapers",
    "resolution": "3840x2160"
  },
  "date-a-live-02.png": {
    "name": "Date A Live 2",
    "anime": "Date A Live",
    "section": "Wallpapers",
    "resolution": "2880x1800"
  },
  "date-a-live-03.png": {
    "name": "Date A Live 3",
    "anime": "Date A Live",
    "section": "Wallpapers",
    "resolution": "1920x1080"
  },
  "date-a-live-04.jpg": {
    "name": "Date A Live 4",
    "anime": "Date A Live",
    "section": "Wallpapers",
    "resolution": "1920x1080"
  },
  "date-a-live-05.png": {
    "name": "Date A Live 5",
    "anime": "Date A Live",
    "section": "Wallpapers",
    "resolution": "3840x2160"
  },
  "death-note-01.jpg": {
    "name": "Death Note 1",
    "anime": "Death Note",
    "section": "Wallpapers",
    "resolution": "1920x1080"
  },
  "death-note-10.png": {
    "name": "Death Note 10",
    "anime": "Death Note",
    "section": "Wallpapers",
    "resolution": "2560x1440"
  },
  "death-note-02.png": {
    "name": "Death Note 2",
    "anime": "Death Note",
    "section": "Wallpapers",
    "resolution": "1920x1080"
  },
  "death-note-03.png": {
    "name": "Death Note 3",
    "anime": "Death Note",
    "section": "Wallpapers",
    "resolution": "3840x2160"
  },
  "death-note-04.jpg": {
    "name": "Death Note 4",
    "anime": "Death Note",
    "section": "Wallpapers",
    "resolution": "2560x1440"
  },
  "death-note-05.jpg": {
    "name": "Death Note 5",
    "anime": "Death Note",
    "section": "Wallpapers",
    "resolution": "1920x1080"
  },
  "death-note-06.jpg": {
    "name": "Death Note 6",
    "anime": "Death Note",
    "section": "Wallpapers",
    "resolution": "2560x1600"
  },
  "death-note-07.jpg": {
    "name": "Death Note 7",
    "anime": "Death Note",
    "section": "Wallpapers",
    "resolution": "1920x1080"
  },
  "death-note-08.jpg": {
    "name": "Death Note 8",
    "anime": "Death Note",
    "section": "Wallpapers",
    "resolution": "1920x1080"
  },
  "death-note-09.jpg": {
    "name": "Death Note 9",
    "anime": "Death Note",
    "section": "Wallpapers",
    "resolution": "1920x1080"
  },
  "frieren-beyond-journeys-end-01.png": {
    "name": "Frieren Beyond Journeys end 1",
    "anime": "Frieren Beyond Journeys end",
    "section": "Wallpapers",
    "resolution": "1920x1290"
  },
  "frieren-beyond-journeys-end-10.png": {
    "name": "Frieren Beyond Journeys end 10",
    "anime": "Frieren Beyond Journeys end",
    "section": "Wallpapers",
    "resolution": "1920x1080"
  },
  "frieren-beyond-journeys-end-11.jpg": {
    "name": "Frieren Beyond Journeys end 11",
    "anime": "Frieren Beyond Journeys end",
    "section": "Wallpapers",
    "resolution": "1920x1080"
  },
  "frieren-beyond-journeys-end-12.jpg": {
    "name": "Frieren Beyond Journeys end 12",
    "anime": "Frieren Beyond Journeys end",
    "section": "Wallpapers",
    "resolution": "3840x2160"
  },
  "frieren-beyond-journeys-end-13.jpg": {
    "name": "Frieren Beyond Journeys end 13",
    "anime": "Frieren Beyond Journeys end",
    "section": "Wallpapers",
    "resolution": "3840x2160"
  },
  "frieren-beyond-journeys-end-14.jpg": {
    "name": "Frieren Beyond Journeys end 14",
    "anime": "Frieren Beyond Journeys end",
    "section": "Wallpapers",
    "resolution": "7680x4320"
  },
  "frieren-beyond-journeys-end-15.jpg": {
    "name": "Frieren Beyond Journeys end 15",
    "anime": "Frieren Beyond Journeys end",
    "section": "Wallpapers",
    "resolution": "1920x1080"
  },
  "frieren-beyond-journeys-end-16.jpg": {
    "name": "Frieren Beyond Journeys end 16",
    "anime": "Frieren Beyond Journeys end",
    "section": "Wallpapers",
    "resolution": "1920x1080"
  },
  "frieren-beyond-journeys-end-17.jpg": {
    "name": "Frieren Beyond Journeys end 17",
    "anime": "Frieren Beyond Journeys end",
    "section": "Wallpapers",
    "resolution": "1920x1080"
  },
  "frieren-beyond-journeys-end-02.jpeg": {
    "name": "Frieren Beyond Journeys end 2",
    "anime": "Frieren Beyond Journeys end",
    "section": "Wallpapers",
    "resolution": "7680x4320"
  },
  "frieren-beyond-journeys-end-03.jpeg": {
    "name": "Frieren Beyond Journeys end 3",
    "anime": "Frieren Beyond Journeys end",
    "section": "Wallpapers",
    "resolution": "3840x2160"
  },
  "frieren-beyond-journeys-end-04.png": {
    "name": "Frieren Beyond Journeys end 4",
    "anime": "Frieren Beyond Journeys end",
    "section": "Wallpapers",
    "resolution": "1920x1080"
  },
  "frieren-beyond-journeys-end-05.jpeg": {
    "name": "Frieren Beyond Journeys end 5",
    "anime": "Frieren Beyond Journeys end",
    "section": "Wallpapers",
    "resolution": "3840x2160"
  },
  "frieren-beyond-journeys-end-06.jpeg": {
    "name": "Frieren Beyond Journeys end 6",
    "anime": "Frieren Beyond Journeys end",
    "section": "Wallpapers",
    "resolution": "3840x2160"
  },
  "frieren-beyond-journeys-end-07.jpeg": {
    "name": "Frieren Beyond Journeys end 7",
    "anime": "Frieren Beyond Journeys end",
    "section": "Wallpapers",
    "resolution": "8418x4161"
  },
  "frieren-beyond-journeys-end-08.jpeg": {
    "name": "Frieren Beyond Journeys end 8",
    "anime": "Frieren Beyond Journeys end",
    "section": "Wallpapers",
    "resolution": "2698x2014"
  },
  "frieren-beyond-journeys-end-09.png": {
    "name": "Frieren Beyond Journeys end 9",
    "anime": "Frieren Beyond Journeys end",
    "section": "Wallpapers",
    "resolution": "3840x2160"
  },
  "fully-blossoms-when-drunk-01.jpg": {
    "name": "Fully Blossoms When Drunk 1",
    "anime": "Fully Blossoms When Drunk",
    "section": "Wallpapers",
    "resolution": "3840x2160"
  },
  "horimiya-01.jpg": {
    "name": "Horimiya 1",
    "anime": "Horimiya",
    "section": "Wallpapers",
    "resolution": "1920x1080"
  },
  "horimiya-02.jpg": {
    "name": "Horimiya 2",
    "anime": "Horimiya",
    "section": "Wallpapers",
    "resolution": "1920x1080"
  },
  "horimiya-03.jpg": {
    "name": "Horimiya 3",
    "anime": "Horimiya",
    "section": "Wallpapers",
    "resolution": "1920x1080"
  },
  "horimiya-04.png": {
    "name": "Horimiya 4",
    "anime": "Horimiya",
    "section": "Wallpapers",
    "resolution": "1920x1080"
  },
  "horimiya-05.jpg": {
    "name": "Horimiya 5",
    "anime": "Horimiya",
    "section": "Wallpapers",
    "resolution": "1920x1080"
  },
  "horimiya-06.jpg": {
    "name": "Horimiya 6",
    "anime": "Horimiya",
    "section": "Wallpapers",
    "resolution": "1920x1080"
  },
  "horimiya-07.jpg": {
    "name": "Horimiya 7",
    "anime": "Horimiya",
    "section": "Wallpapers",
    "resolution": "1920x1080"
  },
  "hyouka-01.png": {
    "name": "Hyouka 1",
    "anime": "Hyouka",
    "section": "Wallpapers",
    "resolution": "1920x1080"
  },
  "hyouka-02.jpg": {
    "name": "Hyouka 2",
    "anime": "Hyouka",
    "section": "Wallpapers",
    "resolution": "3840x2400"
  },
  "hyouka-03.jpg": {
    "name": "Hyouka 3",
    "anime": "Hyouka",
    "section": "Wallpapers",
    "resolution": "2600x1600"
  },
  "hyouka-04.png": {
    "name": "Hyouka 4",
    "anime": "Hyouka",
    "section": "Wallpapers",
    "resolution": "1920x1080"
  },
  "i-want-to-eat-your-pancreas-01.jpg": {
    "name": "I want to eat your pancreas 1",
    "anime": "I want to eat your pancreas",
    "section": "Wallpapers",
    "resolution": "1920x1080"
  },
  "i-want-to-eat-your-pancreas-02.jpg": {
    "name": "I want to eat your pancreas 2",
    "anime": "I want to eat your pancreas",
    "section": "Wallpapers",
    "resolution": "1920x1080"
  },
  "i-want-to-eat-your-pancreas-03.jpg": {
    "name": "I want to eat your pancreas 3",
    "anime": "I want to eat your pancreas",
    "section": "Wallpapers",
    "resolution": "1920x1080"
  },
  "i-want-to-eat-your-pancreas-04.jpg": {
    "name": "I want to eat your pancreas 4",
    "anime": "I want to eat your pancreas",
    "section": "Wallpapers",
    "resolution": "1920x1080"
  },
  "k-on-01.jpg": {
    "name": "K-ON! 1",
    "anime": "K-ON!",
    "section": "Wallpapers",
    "resolution": "1920x1200"
  },
  "k-on-10.png": {
    "name": "K-ON! 10",
    "anime": "K-ON!",
    "section": "Wallpapers",
    "resolution": "1920x1080"
  },
  "k-on-11.png": {
    "name": "K-ON! 11",
    "anime": "K-ON!",
    "section": "Wallpapers",
    "resolution": "1920x1080"
  },
  "k-on-02.jpg": {
    "name": "K-ON! 2",
    "anime": "K-ON!",
    "section": "Wallpapers",
    "resolution": "1920x1080"
  },
  "k-on-03.jpg": {
    "name": "K-ON! 3",
    "anime": "K-ON!",
    "section": "Wallpapers",
    "resolution": "1920x1080"
  },
  "k-on-04.png": {
    "name": "K-ON! 4",
    "anime": "K-ON!",
    "section": "Wallpapers",
    "resolution": "1920x1080"
  },
  "k-on-05.jpg": {
    "name": "K-ON! 5",
    "anime": "K-ON!",
    "section": "Wallpapers",
    "resolution": "1920x1080"
  },
  "k-on-06.jpg": {
    "name": "K-ON! 6",
    "anime": "K-ON!",
    "section": "Wallpapers",
    "resolution": "1920x1200"
  },
  "k-on-07.jpg": {
    "name": "K-ON! 7",
    "anime": "K-ON!",
    "section": "Wallpapers",
    "resolution": "5927x4075"
  },
  "k-on-08.jpg": {
    "name": "K-ON! 8",
    "anime": "K-ON!",
    "section": "Wallpapers",
    "resolution": "6108x4090"
  },
  "k-on-09.jpg": {
    "name": "K-ON! 9",
    "anime": "K-ON!",
    "section": "Wallpapers",
    "resolution": "1920x1080"
  },
  "love-chunibyo-and-other-delusions-01.jpg": {
    "name": "Love, Chunibyo and other delusions 1",
    "anime": "Love, Chunibyo and other delusions",
    "section": "Wallpapers",
    "resolution": "2200x1238"
  },
  "love-chunibyo-and-other-delusions-02.png": {
    "name": "Love, Chunibyo and other delusions 2",
    "anime": "Love, Chunibyo and other delusions",
    "section": "Wallpapers",
    "resolution": "1920x1200"
  },
  "love-chunibyo-and-other-delusions-03.jpg": {
    "name": "Love, Chunibyo and other delusions 3",
    "anime": "Love, Chunibyo and other delusions",
    "section": "Wallpapers",
    "resolution": "1920x1080"
  },
  "love-chunibyo-and-other-delusions-04.jpg": {
    "name": "Love, Chunibyo and other delusions 4",
    "anime": "Love, Chunibyo and other delusions",
    "section": "Wallpapers",
    "resolution": "1920x1080"
  },
  "my-teen-romantic-comedy-01.png": {
    "name": "My Teen Romantic Comedy 1",
    "anime": "My Teen Romantic Comedy",
    "section": "Wallpapers",
    "resolution": "1920x1080"
  },
  "my-teen-romantic-comedy-02.jpg": {
    "name": "My Teen Romantic Comedy 2",
    "anime": "My Teen Romantic Comedy",
    "section": "Wallpapers",
    "resolution": "1920x1080"
  },
  "my-teen-romantic-comedy-03.jpg": {
    "name": "My Teen Romantic Comedy 3",
    "anime": "My Teen Romantic Comedy",
    "section": "Wallpapers",
    "resolution": "1920x1080"
  },
  "neon-genesis-evangelion-01.jpg": {
    "name": "Neon Genesis Evangelion 1",
    "anime": "Neon Genesis Evangelion",
    "section": "Wallpapers",
    "resolution": "3840x2160"
  },
  "neon-genesis-evangelion-02.png": {
    "name": "Neon Genesis Evangelion 2",
    "anime": "Neon Genesis Evangelion",
    "section": "Wallpapers",
    "resolution": "2560x1440"
  },
  "neon-genesis-evangelion-03.png": {
    "name": "Neon Genesis Evangelion 3",
    "anime": "Neon Genesis Evangelion",
    "section": "Wallpapers",
    "resolution": "2560x1440"
  },
  "neon-genesis-evangelion-04.png": {
    "name": "Neon Genesis Evangelion 4",
    "anime": "Neon Genesis Evangelion",
    "section": "Wallpapers",
    "resolution": "1920x1080"
  },
  "orange-01.png": {
    "name": "Orange 1",
    "anime": "Orange",
    "section": "Wallpapers",
    "resolution": "1920x1080"
  },
  "orange-02.png": {
    "name": "Orange 2",
    "anime": "Orange",
    "section": "Wallpapers",
    "resolution": "2560x1440"
  },
  "the-quintessential-quintuplets-01.png": {
    "name": "The Quintessential Quintuplets 1",
    "anime": "The Quintessential Quintuplets",
    "section": "Wallpapers",
    "resolution": "1920x1080"
  },
  "the-quintessential-quintuplets-10.jpg": {
    "name": "The Quintessential Quintuplets 10",
    "anime": "The Quintessential Quintuplets",
    "section": "Wallpapers",
    "resolution": "2718x1699"
  },
  "the-quintessential-quintuplets-02.png": {
    "name": "The Quintessential Quintuplets 2",
    "anime": "The Quintessential Quintuplets",
    "section": "Wallpapers",
    "resolution": "1920x1080"
  },
  "the-quintessential-quintuplets-03.png": {
    "name": "The Quintessential Quintuplets 3",
    "anime": "The Quintessential Quintuplets",
    "section": "Wallpapers",
    "resolution": "1920x1080"
  },
  "the-quintessential-quintuplets-04.jpg": {
    "name": "The Quintessential Quintuplets 4",
    "anime": "The Quintessential Quintuplets",
    "section": "Wallpapers",
    "resolution": "7680x3240"
  },
  "the-quintessential-quintuplets-05.jpg": {
    "name": "The Quintessential Quintuplets 5",
    "anime": "The Quintessential Quintuplets",
    "section": "Wallpapers",
    "resolution": "1920x1080"
  },
  "the-quintessential-quintuplets-06.png": {
    "name": "The Quintessential Quintuplets 6",
    "anime": "The Quintessential Quintuplets",
    "section": "Wallpapers",
    "resolution": "1920x1080"
  },
  "the-quintessential-quintuplets-07.jpg": {
    "name": "The Quintessential Quintuplets 7",
    "anime": "The Quintessential Quintuplets",
    "section": "Wallpapers",
    "resolution": "5184x2916"
  },
  "the-quintessential-quintuplets-08.jpg": {
    "name": "The Quintessential Quintuplets 8",
    "anime": "The Quintessential Quintuplets",
    "section": "Wallpapers",
    "resolution": "1920x1080"
  },
  "the-quintessential-quintuplets-09.jpg": {
    "name": "The Quintessential Quintuplets 9",
    "anime": "The Quintessential Quintuplets",
    "section": "Wallpapers",
    "resolution": "3833x1700"
  },
  "the-tunnel-to-summer-01.jpg": {
    "name": "The Tunnel to summer 1",
    "anime": "The Tunnel to summer",
    "section": "Wallpapers",
    "resolution": "3506x2160"
  },
  "the-tunnel-to-summer-02.jpg": {
    "name": "The Tunnel to summer 2",
    "anime": "The Tunnel to summer",
    "section": "Wallpapers",
    "resolution": "3506x2160"
  },
  "the-tunnel-to-summer-03.png": {
    "name": "The Tunnel to summer 3",
    "anime": "The Tunnel to summer",
    "section": "Wallpapers",
    "resolution": "2856x1606"
  },
  "tokyo-ghoul-01.png": {
    "name": "Tokyo Ghoul 1",
    "anime": "Tokyo Ghoul",
    "section": "Wallpapers",
    "resolution": "1920x1080"
  },
  "tokyo-ghoul-02.jpg": {
    "name": "Tokyo Ghoul 2",
    "anime": "Tokyo Ghoul",
    "section": "Wallpapers",
    "resolution": "1366x964"
  },
  "tokyo-ghoul-03.png": {
    "name": "Tokyo Ghoul 3",
    "anime": "Tokyo Ghoul",
    "section": "Wallpapers",
    "resolution": "1920x1080"
  },
  "tokyo-ghoul-04.png": {
    "name": "Tokyo Ghoul 4",
    "anime": "Tokyo Ghoul",
    "section": "Wallpapers",
    "resolution": "1920x1080"
  },
  "tokyo-ghoul-05.jpg": {
    "name": "Tokyo Ghoul 5",
    "anime": "Tokyo Ghoul",
    "section": "Wallpapers",
    "resolution": "1920x1080"
  },
  "tokyo-ghoul-06.png": {
    "name": "Tokyo Ghoul 6",
    "anime": "Tokyo Ghoul",
    "section": "Wallpapers",
    "resolution": "1920x1080"
  },
  "tokyo-ghoul-07.png": {
    "name": "Tokyo Ghoul 7",
    "anime": "Tokyo Ghoul",
    "section": "Wallpapers",
    "resolution": "7680x4320"
  },
  "vinland-saga-01.png": {
    "name": "Vinland Saga 1",
    "anime": "Vinland Saga",
    "section": "Wallpapers",
    "resolution": "3840x2160"
  },
  "vinland-saga-02.jpeg": {
    "name": "Vinland Saga 2",
    "anime": "Vinland Saga",
    "section": "Wallpapers",
    "resolution": "3370x2099"
  },
  "vinland-saga-03.png": {
    "name": "Vinland Saga 3",
    "anime": "Vinland Saga",
    "section": "Wallpapers",
    "resolution": "6912x3456"
  },
  "vinland-saga-04.jpg": {
    "name": "Vinland Saga 4",
    "anime": "Vinland Saga",
    "section": "Wallpapers",
    "resolution": "3840x2160"
  },
  "vinland-saga-05.jpg": {
    "name": "Vinland Saga 5",
    "anime": "Vinland Saga",
    "section": "Wallpapers",
    "resolution": "2560x1440"
  },
  "violet-evergarden-01.png": {
    "name": "Violet Evergarden 1",
    "anime": "Violet Evergarden",
    "section": "Wallpapers",
    "resolution": "1920x1080"
  },
  "violet-evergarden-02.png": {
    "name": "Violet Evergarden 2",
    "anime": "Violet Evergarden",
    "section": "Wallpapers",
    "resolution": "3840x2160"
  },
  "violet-evergarden-03.jpg": {
    "name": "Violet Evergarden 3",
    "anime": "Violet Evergarden",
    "section": "Wallpapers",
    "resolution": "3840x2160"
  },
  "violet-evergarden-04.png": {
    "name": "Violet Evergarden 4",
    "anime": "Violet Evergarden",
    "section": "Wallpapers",
    "resolution": "1920x1080"
  },
  "violet-evergarden-05.png": {
    "name": "Violet Evergarden 5",
    "anime": "Violet Evergarden",
    "section": "Wallpapers",
    "resolution": "3840x2160"
  },
  "violet-evergarden-06.png": {
    "name": "Violet Evergarden 6",
    "anime": "Violet Evergarden",
    "section": "Wallpapers",
    "resolution": "1920x1080"
  },
  "weathering-with-you-01.jpg": {
    "name": "Weathering with you 1",
    "anime": "Weathering with you",
    "section": "Wallpapers",
    "resolution": "3840x2160"
  },
  "weathering-with-you-02.jpg": {
    "name": "Weathering with you 2",
    "anime": "Weathering with you",
    "section": "Wallpapers",
    "resolution": "1920x1080"
  },
  "weathering-with-you-03.jpg": {
    "name": "Weathering with you 3",
    "anime": "Weathering with you",
    "section": "Wallpapers",
    "resolution": "1920x1080"
  },
  "weathering-with-you-04.jpg": {
    "name": "Weathering with you 4",
    "anime": "Weathering with you",
    "section": "Wallpapers",
    "resolution": "3821x2000"
  },
  "weathering-with-you-05.png": {
    "name": "Weathering with you 5",
    "anime": "Weathering with you",
    "section": "Wallpapers",
    "resolution": "1920x1080"
  },
  "weathering-with-you-06.jpg": {
    "name": "Weathering with you 6",
    "anime": "Weathering with you",
    "section": "Wallpapers",
    "resolution": "4093x2894"
  },
  "your-name-01.jpg": {
    "name": "Your name 1",
    "anime": "Your name",
    "section": "Wallpapers",
    "resolution": "7015x3879"
  },
  "your-name-02.png": {
    "name": "Your name 2",
    "anime": "Your name",
    "section": "Wallpapers",
    "resolution": "1920x1080"
  },
  "your-name-03.jpg": {
    "name": "Your name 3",
    "anime": "Your name",
    "section": "Wallpapers",
    "resolution": "8858x4962"
  },
  "your-name-04.png": {
    "name": "Your name 4",
    "anime": "Your name",
    "section": "Wallpapers",
    "resolution": "1920x1080"
  },
  "your-name-05.png": {
    "name": "Your name 5",
    "anime": "Your name",
    "section": "Wallpapers",
    "resolution": "3840x2160"
  },
  "your-name-06.jpg": {
    "name": "Your name 6",
    "anime": "Your name",
    "section": "Wallpapers",
    "resolution": "3840x2160"
  },
  "chainsaw-man-angel-devil-banner-01.jpg": {
    "name": "Angel Devil (banner)",
    "anime": "Chainsaw Man",
    "section": "Banners",
    "resolution": "9360x3300",
    "set": "Chainsaw Man / Angel Devil"
  },
  "chainsaw-man-angel-devil-profile-01.jpg": {
    "name": "Angel Devil (profile)",
    "anime": "Chainsaw Man",
    "section": "Profiles",
    "resolution": "2808x2808",
    "set": "Chainsaw Man / Angel Devil"
  },
  "chainsaw-man-yoru-banner-01.jpg": {
    "name": "Yoru (banner)",
    "anime": "Chainsaw Man",
    "section": "Banners",
    "resolution": "6144x2166",
    "set": "Chainsaw Man / Yoru"
  },
  "chainsaw-man-yoru-profile-01.jpg": {
    "name": "Yoru (profile)",
    "anime": "Chainsaw Man",
    "section": "Profiles",
    "resolution": "2023x2023",
    "set": "Chainsaw Man / Yoru"
  },
  "frieren-beyond-journeys-end-frieren-banner-01.jpg": {
    "name": "Frieren (banner)",
    "anime": "Frieren Beyond Journeys end",
    "section": "Banners",
    "resolution": "9360x3300",
    "set": "Frieren Beyond Journeys end / Frieren"
  },
  "frieren-beyond-journeys-end-frieren-profile-01.jpg": {
    "name": "Frieren (profile)",
    "anime": "Frieren Beyond Journeys end",
    "section": "Profiles",
    "resolution": "2876x2880",
    "set": "Frieren Beyond Journeys end / Frieren"
  },
  "tokyo-ghoul-ken-banner-01.gif": {
    "name": "Ken (banner)",
    "anime": "Tokyo Ghoul",
    "section": "Banners",
    "resolution": "500x281",
    "set": "Tokyo Ghoul / Ken"
  },
  "tokyo-ghoul-ken-profile-01.jpg": {
    "name": "Ken (profile)",
    "anime": "Tokyo Ghoul",
    "section": "Profiles",
    "resolution": "736x883",
    "set": "Tokyo Ghoul / Ken"
  },
  "berserk-guts-banner-01.jpg": {
    "name": "Guts (banner)",
    "anime": "Berserk",
    "section": "Banners",
    "resolution": "2048x818",
    "set": "Berserk / Guts"
  },
  "berserk-guts-profile-01.jpg": {
    "name": "Guts (profile)",
    "anime": "Berserk",
    "section": "Profiles",
    "resolution": "1160x1160",
    "set": "Berserk / Guts"
  },
  "chainsaw-man-asa-banner-01.png": {
    "name": "Asa (banner)",
    "anime": "Chainsaw Man",
    "section": "Banners",
    "resolution": "1003x354",
    "set": "Chainsaw Man / Asa"
  },
  "chainsaw-man-asa-profile-01.jpg": {
    "name": "Asa (profile)",
    "anime": "Chainsaw Man",
    "section": "Profiles",
    "resolution": "1472x1472",
    "set": "Chainsaw Man / Asa"
  },
  "chainsaw-man-denji-banner-01.jpg": {
    "name": "Denji (banner 1)",
    "anime": "Chainsaw Man",
    "section": "Banners",
    "resolution": "7020x2475",
    "set": "Chainsaw Man / Denji"
  },
  "chainsaw-man-denji-banner-02.jpg": {
    "name": "Denji (banner 2)",
    "anime": "Chainsaw Man",
    "section": "Banners",
    "resolution": "2048x818",
    "set": "Chainsaw Man / Denji"
  },
  "chainsaw-man-denji-banner-03.jpg": {
    "name": "Denji (banner 3)",
    "anime": "Chainsaw Man",
    "section": "Banners",
    "resolution": "7020x2475",
    "set": "Chainsaw Man / Denji"
  },
  "chainsaw-man-denji-banner-04.png": {
    "name": "Denji (banner 4)",
    "anime": "Chainsaw Man",
    "section": "Banners",
    "resolution": "3488x1216",
    "set": "Chainsaw Man / Denji"
  },
  "chainsaw-man-denji-profile-01.jpg": {
    "name": "Denji (profile 1)",
    "anime": "Chainsaw Man",
    "section": "Profiles",
    "resolution": "1173x1173",
    "set": "Chainsaw Man / Denji"
  },
  "chainsaw-man-denji-profile-02.jpg": {
    "name": "Denji (profile 2)",
    "anime": "Chainsaw Man",
    "section": "Profiles",
    "resolution": "1472x1472",
    "set": "Chainsaw Man / Denji"
  },
  "chainsaw-man-denji-profile-03.jpg": {
    "name": "Denji (profile 3)",
    "anime": "Chainsaw Man",
    "section": "Profiles",
    "resolution": "1308x1308",
    "set": "Chainsaw Man / Denji"
  },
  "chainsaw-man-denji-profile-04.png": {
    "name": "Denji (profile 4)",
    "anime": "Chainsaw Man",
    "section": "Profiles",
    "resolution": "2048x2080",
    "set": "Chainsaw Man / Denji"
  },
  "chainsaw-man-makima-banner-01.gif": {
    "name": "Makima (banner 1)",
    "anime": "Chainsaw Man",
    "section": "Banners",
    "resolution": "800x282",
    "set": "Chainsaw Man / Makima"
  },
  "chainsaw-man-makima-banner-02.jpg": {
    "name": "Makima (banner 2)",
    "anime": "Chainsaw Man",
    "section": "Banners",
    "resolution": "9360x3300",
    "set": "Chainsaw Man / Makima"
  },
  "chainsaw-man-makima-banner-03.jpg": {
    "name": "Makima (banner 3)",
    "anime": "Chainsaw Man",
    "section": "Banners",
    "resolution": "2048x818",
    "set": "Chainsaw Man / Makima"
  },
  "chainsaw-man-makima-profile-01.jpg": {
    "name": "Makima (profile 1)",
    "anime": "Chainsaw Man",
    "section": "Profiles",
    "resolution": "736x736",
    "set": "Chainsaw Man / Makima"
  },
  "chainsaw-man-makima-profile-02.jpg": {
    "name": "Makima (profile 2)",
    "anime": "Chainsaw Man",
    "section": "Profiles",
    "resolution": "4320x4320",
    "set": "Chainsaw Man / Makima"
  },
  "chainsaw-man-makima-profile-03.jpg": {
    "name": "Makima (profile 3)",
    "anime": "Chainsaw Man",
    "section": "Profiles",
    "resolution": "1298x1298",
    "set": "Chainsaw Man / Makima"
  },
  "chainsaw-man-quanxi-banner-01.jpg": {
    "name": "Quanxi (banner)",
    "anime": "Chainsaw Man",
    "section": "Banners",
    "resolution": "11700x4680",
    "set": "Chainsaw Man / Quanxi"
  },
  "chainsaw-man-quanxi-profile-01.jpg": {
    "name": "Quanxi (profile)",
    "anime": "Chainsaw Man",
    "section": "Profiles",
    "resolution": "3680x3680",
    "set": "Chainsaw Man / Quanxi"
  },
  "chainsaw-man-reze-banner-01.jpg": {
    "name": "Reze (banner)",
    "anime": "Chainsaw Man",
    "section": "Banners",
    "resolution": "9360x3300",
    "set": "Chainsaw Man / Reze"
  },
  "chainsaw-man-reze-profile-01.jpg": {
    "name": "Reze (profile)",
    "anime": "Chainsaw Man",
    "section": "Profiles",
    "resolution": "2944x2944",
    "set": "Chainsaw Man / Reze"
  },
  "neon-genesis-evangelion-shinji-banner-01.jpg": {
    "name": "Shinji (banner 1)",
    "anime": "Neon Genesis Evangelion",
    "section": "Banners",
    "resolution": "2048x818",
    "set": "Neon Genesis Evangelion / Shinji"
  },
  "neon-genesis-evangelion-shinji-banner-02.jpg": {
    "name": "Shinji (banner 2)",
    "anime": "Neon Genesis Evangelion",
    "section": "Banners",
    "resolution": "2048x818",
    "set": "Neon Genesis Evangelion / Shinji"
  },
  "neon-genesis-evangelion-shinji-banner-03.jpg": {
    "name": "Shinji (banner 3)",
    "anime": "Neon Genesis Evangelion",
    "section": "Banners",
    "resolution": "2048x818",
    "set": "Neon Genesis Evangelion / Shinji"
  },
  "neon-genesis-evangelion-shinji-profile-01.jpg": {
    "name": "Shinji (profile 1)",
    "anime": "Neon Genesis Evangelion",
    "section": "Profiles",
    "resolution": "1320x1320",
    "set": "Neon Genesis Evangelion / Shinji"
  },
  "neon-genesis-evangelion-shinji-profile-02.jpg": {
    "name": "Shinji (profile 2)",
    "anime": "Neon Genesis Evangelion",
    "section": "Profiles",
    "resolution": "916x916",
    "set": "Neon Genesis Evangelion / Shinji"
  },
  "neon-genesis-evangelion-shinji-profile-03.jpg": {
    "name": "Shinji (profile 3)",
    "anime": "Neon Genesis Evangelion",
    "section": "Profiles",
    "resolution": "2944x2944",
    "set": "Neon Genesis Evangelion / Shinji"
  },
  "vinland-saga-thorfinn-banner-01.jpg": {
    "name": "Thorfinn (banner 1)",
    "anime": "Vinland Saga",
    "section": "Banners",
    "resolution": "9360x3300",
    "set": "Vinland Saga / Thorfinn"
  },
  "vinland-saga-thorfinn-banner-02.jpg": {
    "name": "Thorfinn (banner 2)",
    "anime": "Vinland Saga",
    "section": "Banners",
    "resolution": "6144x2166",
    "set": "Vinland Saga / Thorfinn"
  },
  "vinland-saga-thorfinn-profile-01.jpg": {
    "name": "Thorfinn (profile 1)",
    "anime": "Vinland Saga",
    "section": "Profiles",
    "resolution": "4320x4320",
    "set": "Vinland Saga / Thorfinn"
  },
  "vinland-saga-thorfinn-profile-02.jpg": {
    "name": "Thorfinn (profile 2)",
    "anime": "Vinland Saga",
    "section": "Profiles",
    "resolution": "2208x2205",
    "set": "Vinland Saga / Thorfinn"
  }
}